README.rst
setup.py
docs/HISTORY.txt
docs/INSTALL.txt
docs/LICENSE.GPL
docs/LICENSE.txt
docs/TODO.txt
ipnext/__init__.py
ipnext.viewlet.blog.egg-info/PKG-INFO
ipnext.viewlet.blog.egg-info/SOURCES.txt
ipnext.viewlet.blog.egg-info/dependency_links.txt
ipnext.viewlet.blog.egg-info/entry_points.txt
ipnext.viewlet.blog.egg-info/namespace_packages.txt
ipnext.viewlet.blog.egg-info/not-zip-safe
ipnext.viewlet.blog.egg-info/requires.txt
ipnext.viewlet.blog.egg-info/top_level.txt
ipnext/viewlet/__init__.py
ipnext/viewlet/blog/__init__.py
ipnext/viewlet/blog/configure.zcml
ipnext/viewlet/blog/interfaces.py
ipnext/viewlet/blog/testing.py
ipnext/viewlet/blog/tests.py
ipnext/viewlet/blog/browser/__init__.py
ipnext/viewlet/blog/browser/configure.zcml
ipnext/viewlet/blog/browser/controllers.py
ipnext/viewlet/blog/browser/interfaces.py
ipnext/viewlet/blog/browser/viewlets.py
ipnext/viewlet/blog/browser/stylesheets/blog-viewlet.css
ipnext/viewlet/blog/browser/templates/blog_viewlet.pt
ipnext/viewlet/blog/profiles/default/browserlayer.xml
ipnext/viewlet/blog/profiles/default/cssregistry.xml
ipnext/viewlet/blog/profiles/default/metadata.xml
ipnext/viewlet/blog/profiles/default/registry.xml
ipnext/viewlet/blog/profiles/default/viewlets.xml