Metadata-Version: 1.0
Name: ipnext.viewlet.blog
Version: 0.3.4
Summary: Display a relevant post for this page
Home-page: http://svn.plone.org/svn/collective/
Author: zedr
Author-email: zedr@ipnext.it
License: GPL
Platform: UNKNOWN
Classifier: Framework :: Plone
Classifier: Programming Language :: Python
